FineEx/__init__.py
FineEx/Middleware/__init__.py
FineEx/Middleware/Message/__init__.py
FineEx/Middleware/Message/pyemail.py
FineEx/Middleware/Message/pyphone.py
FineEx/Middleware/Message/pypushdeer.py
FineEx/Middleware/Message/pysms.py
FineEx/Middleware/Message/pywechat.py
FineEx.Cloud.Middle.Message-1.0.3.dist-info/LICENSE
FineEx.Cloud.Middle.Message-1.0.3.dist-info/METADATA
FineEx.Cloud.Middle.Message-1.0.3.dist-info/WHEEL
FineEx.Cloud.Middle.Message-1.0.3.dist-info/top_level.txt
FineEx.Cloud.Middle.Message-1.0.3.dist-info/RECORD
