Metadata-Version: 2.1
Name: FineEx.Cloud.Middle.Message
Version: 1.0.3
Summary: 发网供应链消息推送组件
Author-email: liuchunyang <liuchunyang@fineex.com>
Project-URL: Homepage, https://github.com/JokkerLiu/fineex.cloud.middle.message
Project-URL: Issues, https://github.com/JokkerLiu/fineex.cloud.middle.message/issues
Classifier: Programming Language :: Python :: 3
Classifier: License :: OSI Approved :: MIT License
Classifier: Operating System :: OS Independent
Requires-Python: >=3.7
License-File: LICENSE
Requires-Dist: requests
Requires-Dist: aliyun-python-sdk-core
Requires-Dist: aliyun-python-sdk-dysmsapi
Requires-Dist: mailutils
